docs/source/conf.py
raspidevkit/__init__.py
raspidevkit/__interface.py
raspidevkit/__logger.py
raspidevkit/constants.py
raspidevkit/machine.py
raspidevkit/utils.py
raspidevkit/devices/__init__.py
raspidevkit/devices/base.py
raspidevkit/devices/arduino/button.py
raspidevkit/devices/arduino/dht.py
raspidevkit/devices/arduino/hall_effect_sensor.py
raspidevkit/devices/arduino/led.py
raspidevkit/devices/arduino/relay.py
raspidevkit/devices/arduino/servo_motor.py
raspidevkit/devices/drivers/dc_motor/base.py
raspidevkit/devices/drivers/dc_motor/l293d.py
raspidevkit/devices/drivers/dc_motor/l298n.py
raspidevkit/devices/gpio/button.py
raspidevkit/devices/gpio/buzzer.py
raspidevkit/devices/gpio/dht_sensor.py
raspidevkit/devices/gpio/hall_effect_sensor.py
raspidevkit/devices/gpio/led.py
raspidevkit/devices/gpio/light_sensor.py
raspidevkit/devices/gpio/pir_motion_sensor.py
raspidevkit/devices/gpio/relay.py
raspidevkit/devices/gpio/rgb_led.py
raspidevkit/devices/gpio/servo_motor.py
raspidevkit/devices/gpio/ultrasonic_sensor.py
raspidevkit/devices/serial/arduino.py
raspidevkit/devices/serial/sim808.py
raspidevkit/templates/.clang-format
raspidevkit/templates/arduino_template.ino
tests/test_arduino.py
tests/test_drivers.py
tests/test_gpio_devices.py
raspidevkit-0.0.6.2.dist-info/LICENSE
raspidevkit-0.0.6.2.dist-info/METADATA
raspidevkit-0.0.6.2.dist-info/WHEEL
raspidevkit-0.0.6.2.dist-info/top_level.txt
raspidevkit-0.0.6.2.dist-info/RECORD
