Metadata-Version: 2.1
Name: raspidevkit
Version: 0.0.6.2
Summary: Easily control devices with Raspberry Pi
Home-page: https://github.com/raspidevkit/raspidevkit
Author: DailyLollipops
Author-email: DailyLollipops <clarencemadrigal84@gmail.com>
License: MIT License
Project-URL: Homepage, https://github.com/raspidevkit/raspidevkit
Keywords: python,raspberry-pi,iot,arduino
Classifier: License :: OSI Approved :: MIT License
Classifier: Programming Language :: Python
Classifier: Programming Language :: Python :: 3
Requires-Python: >=3.9
License-File: LICENSE
Requires-Dist: setuptools
Requires-Dist: fake-rpi
Requires-Dist: pyserial
Requires-Dist: smbus2
Provides-Extra: dev
Requires-Dist: sphinx ; extra == 'dev'
Requires-Dist: sphinx-rtd-theme ; extra == 'dev'
Requires-Dist: setuptools ; extra == 'dev'
Requires-Dist: wheel ; extra == 'dev'
Requires-Dist: pytest ; extra == 'dev'
